Metadata-Version: 2.1
Name: GoldenX
Version: 0.1
Summary: @rrrrrf
Author: Mohammed
Classifier: Programming Language :: Python :: 3
Classifier: Operating System :: OS Independent
Classifier: License :: OSI Approved :: MIT License
License-File: LICENSE.txt
